{
    "sections":[
                {
                "id":1,
                "type":"news",
                "name":"Dernières actu près de chez vous",
                "news":[
                        {
                        "id":1,
                        "title":"Actu n°1",
                        "description":"Lorem ipsum dolor sit amet, consectetur adipiscing elit. Phasellus eu lorem sit amet nibh pretium aliquet sit amet at nulla. Cras malesuada ligula arcu, luctus laoreet turpis rhoncus eu. Proin mattis, orci et lobortis finibus, lacus erat fermentum massa, sit amet tempus elit massa eu enim. Etiam mattis, dui ut mollis blandit, eros risus rutrum metus, ac ornare mauris mi sed augue. Duis convallis massa id metus convallis mattis. Nunc vestibulum feugiat nisl eget tempor. Nam consectetur magna augue, quis condimentum sem interdum sed.",
                        "image_url":"https://www.challenges.fr/assets/img/2015/02/13/cover-r4x3w1000-578e978867c47-en-images-projet-un-architecte-ancre-la-nature-au-c-ur.jpg",
                        "tag":{
                        "id":1,
                        "name":"Actualité"
                        }
                        },
                        {
                        "id":2,
                        "title":"Actu n°2",
                        "description":"Nunc quis purus pellentesque, finibus eros eu, pretium justo. Maecenas tristique commodo semper. In hac habitasse platea dictumst. Duis fringilla luctus ultrices. Proin ac fermentum turpis. Sed eu semper nisl, quis venenatis enim. Phasellus cursus nibh lectus, in maximus turpis pretium non. Curabitur rhoncus gravida nunc. Vivamus pulvinar consequat magna non tincidunt. In hac habitasse platea dictumst.",
                        "image_url":"https://www.interoute-ville.com/theme/interoute_desktop/images/footer-content-image.jpg",
                        "tag":{
                        "id":1,
                        "name":"Actualité"
                        }
                        },
                        {
                        "id":3,
                        "title":"Actu n°3",
                        "description":"Suspendisse nec faucibus risus. Sed venenatis diam varius, commodo massa vitae, pellentesque ligula. Nunc sollicitudin sem sem. Phasellus vitae elit feugiat, suscipit orci sed, sodales lectus. Sed efficitur enim sed hendrerit imperdiet. Cras condimentum feugiat mi, varius lobortis risus pellentesque id. Vivamus blandit ipsum et consequat imperdiet. Suspendisse in dolor orci.",
                        "image_url":"https://res.cloudinary.com/simpleview/image/upload/c_fill,h_910,q_45,w_1206/crm/quebec/jardin-St-Roch_BD508EA9-75A1-4DE8-BCC4FB9C4821C7DC_12e34cd1-ae5b-4da4-839b34d4c7bf1d7e.jpg",
                        "tag":{
                        "id":1,
                        "name":"Actualité"
                        }
                        },
                        {
                        "id":4,
                        "title":"Actu n°4",
                        "description":"Ut iaculis tempor tellus, ut congue lacus porttitor pretium. Integer lacus ex, malesuada at fermentum nec, sagittis sed libero. Sed in nibh et sem cursus volutpat sit amet tempor sapien. Aliquam porta viverra nibh. Curabitur lectus orci, accumsan sit amet ante vitae, accumsan tincidunt sapien. Nam sed aliquam turpis. Maecenas rhoncus euismod turpis, nec molestie est vestibulum non. Fusce ultrices, justo ut tristique tempor, arcu velit dignissim lacus, sed porttitor orci purus sed ligula. Integer et blandit erat, at auctor nisl.",
                        "image_url":"https://encrypted-tbn0.gstatic.com/images?q=tbn:ANd9GcRyJJZIbhwGsZOuysrw0IdQ9Htt2GTqCzRTVEhN-w4d5bNQchj1",
                        "tag":{
                        "id":1,
                        "name":"Actualité"
                        }
                        },
                        {
                        "id":5,
                        "title":"Actu n°5",
                        "description":"Maecenas rhoncus metus vitae erat vehicula, in venenatis nisl semper. Duis ante nulla, maximus sed magna nec, posuere interdum quam. Pellentesque vehicula turpis et ipsum lobortis viverra. Etiam vel quam urna. Etiam feugiat, libero non congue consequat, augue ipsum sollicitudin leo, a gravida lacus dui at nunc. Sed ut orci velit. Sed ullamcorper hendrerit magna, sed placerat felis fringilla pulvinar. Nullam vel erat volutpat, eleifend felis ac, efficitur massa. Donec sit amet leo enim.",
                        "image_url":"https://www.chartres.fr/fileadmin/_processed_/f/f/csm_Rubrique-planDeLaVille_1920x1200_ab62430e28.jpg",
                        "tag":{
                        "id":1,
                        "name":"Actualité"
                        }
                        }
                        ]
                },
                {
                "id":2,
                "type":"object",
                "name":"Derniers objets partagés",
                "adverts":[
                           {
                           "id":1,
                           "title":"Objet n°1",
                           "description":"Lorem ipsum dolor sit amet, consectetur adipiscing elit. Phasellus eu lorem sit amet nibh pretium aliquet sit amet at nulla. Cras malesuada ligula arcu, luctus laoreet turpis rhoncus eu. Proin mattis, orci et lobortis finibus, lacus erat fermentum massa, sit amet tempus elit massa eu enim. Etiam mattis, dui ut mollis blandit, eros risus rutrum metus, ac ornare mauris mi sed augue. Duis convallis massa id metus convallis mattis. Nunc vestibulum feugiat nisl eget tempor. Nam consectetur magna augue, quis condimentum sem interdum sed.",
                           "city":"Paris 18",
                           "image_url":"https://www.olapromo.com/reduction/coupon-reduction-bricolage.jpg",
                           "price":"204",
                           "tag":{
                           "id":2,
                           "name":"Bricolage"
                           },
                           "user": {
                           "id":40829,
                           "firstname":"thomas",
                           "lastname":"donninger",
                           "email":"tom@voodoo.fr",
                           "image_url":"https://www.tm-town.com/assets/default_male600x600-79218392a28f78af249216e097aaf683.png"
                           }
                           },
                           {
                           "id":2,
                           "title":"Objet n°2",
                           "description":"Lorem ipsum dolor sit amet, consectetur adipiscing elit. Phasellus eu lorem sit amet nibh pretium aliquet sit amet at nulla. Cras malesuada ligula arcu, luctus laoreet turpis rhoncus eu. Proin mattis, orci et lobortis finibus, lacus erat fermentum massa, sit amet tempus elit massa eu enim. Etiam mattis, dui ut mollis blandit, eros risus rutrum metus, ac ornare mauris mi sed augue. Duis convallis massa id metus convallis mattis. Nunc vestibulum feugiat nisl eget tempor. Nam consectetur magna augue, quis condimentum sem interdum sed.",
                           "city":"Paris 18",
                           "image_url":"https://www.olapromo.com/reduction/coupon-reduction-bricolage.jpg",
                           "price":"21",
                           "tag":{
                           "id":2,
                           "name":"Bricolage"
                           },
                           "user": {
                           "id":40830,
                           "firstname":"Jeanne",
                           "lastname":"Dubois",
                           "email":"jeanne@voodoo.fr",
                           "image_url":"https://image.flaticon.com/icons/png/512/163/163833.png"
                           }
                           },
                           {
                           "id":3,
                           "title":"Objet n°3",
                           "description":"Lorem ipsum dolor sit amet, consectetur adipiscing elit. Phasellus eu lorem sit amet nibh pretium aliquet sit amet at nulla. Cras malesuada ligula arcu, luctus laoreet turpis rhoncus eu. Proin mattis, orci et lobortis finibus, lacus erat fermentum massa, sit amet tempus elit massa eu enim. Etiam mattis, dui ut mollis blandit, eros risus rutrum metus, ac ornare mauris mi sed augue. Duis convallis massa id metus convallis mattis. Nunc vestibulum feugiat nisl eget tempor. Nam consectetur magna augue, quis condimentum sem interdum sed.",
                           "city":"Paris 18",
                           "image_url":"https://www.olapromo.com/reduction/coupon-reduction-bricolage.jpg",
                           "price":"32",
                           "tag":{
                           "id":2,
                           "name":"Bricolage"
                           },
                           "user": {
                           "id":40830,
                           "firstname":"Jeanne",
                           "lastname":"Dubois",
                           "email":"jeanne@voodoo.fr",
                           "image_url":"https://image.flaticon.com/icons/png/512/163/163833.png"
                           }
                           },
                           {
                           "id":4,
                           "title":"Objet n°4",
                           "description":"Lorem ipsum dolor sit amet, consectetur adipiscing elit. Phasellus eu lorem sit amet nibh pretium aliquet sit amet at nulla. Cras malesuada ligula arcu, luctus laoreet turpis rhoncus eu. Proin mattis, orci et lobortis finibus, lacus erat fermentum massa, sit amet tempus elit massa eu enim. Etiam mattis, dui ut mollis blandit, eros risus rutrum metus, ac ornare mauris mi sed augue. Duis convallis massa id metus convallis mattis. Nunc vestibulum feugiat nisl eget tempor. Nam consectetur magna augue, quis condimentum sem interdum sed.",
                           "city":"Paris 18",
                           "image_url":"https://www.olapromo.com/reduction/coupon-reduction-bricolage.jpg",
                           "price":"11",
                           "tag":{
                           "id":2,
                           "name":"Bricolage"
                           },
                           "user": {
                           "id":40829,
                           "firstname":"thomas",
                           "lastname":"donninger",
                           "email":"tom@voodoo.fr",
                           "image_url":"https://www.tm-town.com/assets/default_male600x600-79218392a28f78af249216e097aaf683.png"
                           }
                           },
                           {
                           "id":5,
                           "title":"Objet n°5",
                           "description":"Lorem ipsum dolor sit amet, consectetur adipiscing elit. Phasellus eu lorem sit amet nibh pretium aliquet sit amet at nulla. Cras malesuada ligula arcu, luctus laoreet turpis rhoncus eu. Proin mattis, orci et lobortis finibus, lacus erat fermentum massa, sit amet tempus elit massa eu enim. Etiam mattis, dui ut mollis blandit, eros risus rutrum metus, ac ornare mauris mi sed augue. Duis convallis massa id metus convallis mattis. Nunc vestibulum feugiat nisl eget tempor. Nam consectetur magna augue, quis condimentum sem interdum sed.",
                           "city":"Paris 18",
                           "image_url":"https://www.olapromo.com/reduction/coupon-reduction-bricolage.jpg",
                           "price":"10",
                           "tag":{
                           "id":2,
                           "name":"Bricolage"
                           },
                           "user": {
                           "id":40830,
                           "firstname":"Jeanne",
                           "lastname":"Dubois",
                           "email":"jeanne@voodoo.fr",
                           "image_url":"https://image.flaticon.com/icons/png/512/163/163833.png"
                           }
                           }
                           ]
                },
                {
                "id":3,
                "type":"service",
                "name":"Derniers services proposés",
                "adverts":[
                           {
                           "id":1,
                           "title":"Service n°1",
                           "description":"Lorem ipsum dolor sit amet, consectetur adipiscing elit. Phasellus eu lorem sit amet nibh pretium aliquet sit amet at nulla. Cras malesuada ligula arcu, luctus laoreet turpis rhoncus eu. Proin mattis, orci et lobortis finibus, lacus erat fermentum massa, sit amet tempus elit massa eu enim. Etiam mattis, dui ut mollis blandit, eros risus rutrum metus, ac ornare mauris mi sed augue. Duis convallis massa id metus convallis mattis. Nunc vestibulum feugiat nisl eget tempor. Nam consectetur magna augue, quis condimentum sem interdum sed.",
                           "city":"Paris 18",
                           "image_url":"https://www.anact.fr/sites/anact/files/styles/780x503/public/aide-domicile-cas-entreprise.png?itok=9ig_Pm4l",
                           "price":"22",
                           "tag":{
                           "id":3,
                           "name":"Aide à domicile"
                           },
                           "user": {
                           "id":40829,
                           "firstname":"thomas",
                           "lastname":"donninger",
                           "email":"tom@voodoo.fr",
                           "image_url":"https://www.tm-town.com/assets/default_male600x600-79218392a28f78af249216e097aaf683.png"
                           }
                           },
                           {
                           "id":2,
                           "title":"Service n°2",
                           "description":"Lorem ipsum dolor sit amet, consectetur adipiscing elit. Phasellus eu lorem sit amet nibh pretium aliquet sit amet at nulla. Cras malesuada ligula arcu, luctus laoreet turpis rhoncus eu. Proin mattis, orci et lobortis finibus, lacus erat fermentum massa, sit amet tempus elit massa eu enim. Etiam mattis, dui ut mollis blandit, eros risus rutrum metus, ac ornare mauris mi sed augue. Duis convallis massa id metus convallis mattis. Nunc vestibulum feugiat nisl eget tempor. Nam consectetur magna augue, quis condimentum sem interdum sed.",
                           "city":"Paris 18",
                           "image_url":"https://encrypted-tbn0.gstatic.com/images?q=tbn:ANd9GcQuvP0Ijdg9Nf3gI2h83aMz33fl_XLsqpKZPGc0tX_6RQmLa83O",
                           "price":"25",
                           "tag":{
                           "id":4,
                           "name":"Travaux"
                           },
                           "user": {
                           "id":40830,
                           "firstname":"Jeanne",
                           "lastname":"Dubois",
                           "email":"jeanne@voodoo.fr",
                           "image_url":"https://image.flaticon.com/icons/png/512/163/163833.png"
                           }
                           },
                           {
                           "id":3,
                           "title":"Service n°3",
                           "description":"Lorem ipsum dolor sit amet, consectetur adipiscing elit. Phasellus eu lorem sit amet nibh pretium aliquet sit amet at nulla. Cras malesuada ligula arcu, luctus laoreet turpis rhoncus eu. Proin mattis, orci et lobortis finibus, lacus erat fermentum massa, sit amet tempus elit massa eu enim. Etiam mattis, dui ut mollis blandit, eros risus rutrum metus, ac ornare mauris mi sed augue. Duis convallis massa id metus convallis mattis. Nunc vestibulum feugiat nisl eget tempor. Nam consectetur magna augue, quis condimentum sem interdum sed.",
                           "city":"Paris 18",
                           "image_url":"https://encrypted-tbn0.gstatic.com/images?q=tbn:ANd9GcQuvP0Ijdg9Nf3gI2h83aMz33fl_XLsqpKZPGc0tX_6RQmLa83O",
                           "price":"40",
                           "tag":{
                           "id":4,
                           "name":"Travaux"
                           },
                           "user": {
                           "id":40829,
                           "firstname":"thomas",
                           "lastname":"donninger",
                           "email":"tom@voodoo.fr",
                           "image_url":"https://www.tm-town.com/assets/default_male600x600-79218392a28f78af249216e097aaf683.png"
                           }
                           },
                           {
                           "id":4,
                           "title":"Service n°4",
                           "description":"Lorem ipsum dolor sit amet, consectetur adipiscing elit. Phasellus eu lorem sit amet nibh pretium aliquet sit amet at nulla. Cras malesuada ligula arcu, luctus laoreet turpis rhoncus eu. Proin mattis, orci et lobortis finibus, lacus erat fermentum massa, sit amet tempus elit massa eu enim. Etiam mattis, dui ut mollis blandit, eros risus rutrum metus, ac ornare mauris mi sed augue. Duis convallis massa id metus convallis mattis. Nunc vestibulum feugiat nisl eget tempor. Nam consectetur magna augue, quis condimentum sem interdum sed.",
                           "city":"Paris 18",
                           "image_url":"https://www.anact.fr/sites/anact/files/styles/780x503/public/aide-domicile-cas-entreprise.png?itok=9ig_Pm4l",
                           "price":"2",
                           "tag":{
                           "id":3,
                           "name":"Aide à domicile"
                           },
                           "user": {
                           "id":40830,
                           "firstname":"Jeanne",
                           "lastname":"Dubois",
                           "email":"jeanne@voodoo.fr",
                           "image_url":"https://image.flaticon.com/icons/png/512/163/163833.png"
                           }
                           },
                           {
                           "id":5,
                           "title":"Objet n°5",
                           "description":"Lorem ipsum dolor sit amet, consectetur adipiscing elit. Phasellus eu lorem sit amet nibh pretium aliquet sit amet at nulla. Cras malesuada ligula arcu, luctus laoreet turpis rhoncus eu. Proin mattis, orci et lobortis finibus, lacus erat fermentum massa, sit amet tempus elit massa eu enim. Etiam mattis, dui ut mollis blandit, eros risus rutrum metus, ac ornare mauris mi sed augue. Duis convallis massa id metus convallis mattis. Nunc vestibulum feugiat nisl eget tempor. Nam consectetur magna augue, quis condimentum sem interdum sed.",
                           "city":"Paris 18",
                           "image_url":"https://www.anact.fr/sites/anact/files/styles/780x503/public/aide-domicile-cas-entreprise.png?itok=9ig_Pm4l",
                           "price":"20",
                           "tag":{
                           "id":3,
                           "name":"Aide à domicile"
                           },
                           "user": {
                           "id":40829,
                           "firstname":"thomas",
                           "lastname":"donninger",
                           "email":"tom@voodoo.fr",
                           "image_url":"https://www.tm-town.com/assets/default_male600x600-79218392a28f78af249216e097aaf683.png"
                           }
                           }
                           ]
                },
                {
                "id":3,
                "type":"request",
                "name":"Aidez vos voisins",
                "adverts":[
                           {
                           "id":1,
                           "title":"Demande n°1",
                           "description":"Lorem ipsum dolor sit amet, consectetur adipiscing elit. Phasellus eu lorem sit amet nibh pretium aliquet sit amet at nulla. Cras malesuada ligula arcu, luctus laoreet turpis rhoncus eu. Proin mattis, orci et lobortis finibus, lacus erat fermentum massa, sit amet tempus elit massa eu enim. Etiam mattis, dui ut mollis blandit, eros risus rutrum metus, ac ornare mauris mi sed augue. Duis convallis massa id metus convallis mattis. Nunc vestibulum feugiat nisl eget tempor. Nam consectetur magna augue, quis condimentum sem interdum sed.",
                           "city":"Paris 18",
                           "image_url":"https://www.anact.fr/sites/anact/files/styles/780x503/public/aide-domicile-cas-entreprise.png?itok=9ig_Pm4l",
                           "price":"100",
                           "tag":{
                           "id":3,
                           "name":"Aide à domicile"
                           },
                           "user": {
                           "id":40830,
                           "firstname":"Jeanne",
                           "lastname":"Dubois",
                           "email":"jeanne@voodoo.fr",
                           "image_url":"https://image.flaticon.com/icons/png/512/163/163833.png"
                           }
                           },
                           {
                           "id":2,
                           "title":"Demande n°2",
                           "description":"Lorem ipsum dolor sit amet, consectetur adipiscing elit. Phasellus eu lorem sit amet nibh pretium aliquet sit amet at nulla. Cras malesuada ligula arcu, luctus laoreet turpis rhoncus eu. Proin mattis, orci et lobortis finibus, lacus erat fermentum massa, sit amet tempus elit massa eu enim. Etiam mattis, dui ut mollis blandit, eros risus rutrum metus, ac ornare mauris mi sed augue. Duis convallis massa id metus convallis mattis. Nunc vestibulum feugiat nisl eget tempor. Nam consectetur magna augue, quis condimentum sem interdum sed.",
                           "city":"Paris 18",
                           "image_url":"https://encrypted-tbn0.gstatic.com/images?q=tbn:ANd9GcQuvP0Ijdg9Nf3gI2h83aMz33fl_XLsqpKZPGc0tX_6RQmLa83O",
                           "price":"10",
                           "tag":{
                           "id":4,
                           "name":"Travaux"
                           },
                           "user": {
                           "id":40829,
                           "firstname":"thomas",
                           "lastname":"donninger",
                           "email":"tom@voodoo.fr",
                           "image_url":"https://www.tm-town.com/assets/default_male600x600-79218392a28f78af249216e097aaf683.png"
                           }
                           },
                           {
                           "id":3,
                           "title":"Demande n°3",
                           "description":"Lorem ipsum dolor sit amet, consectetur adipiscing elit. Phasellus eu lorem sit amet nibh pretium aliquet sit amet at nulla. Cras malesuada ligula arcu, luctus laoreet turpis rhoncus eu. Proin mattis, orci et lobortis finibus, lacus erat fermentum massa, sit amet tempus elit massa eu enim. Etiam mattis, dui ut mollis blandit, eros risus rutrum metus, ac ornare mauris mi sed augue. Duis convallis massa id metus convallis mattis. Nunc vestibulum feugiat nisl eget tempor. Nam consectetur magna augue, quis condimentum sem interdum sed.",
                           "city":"Paris 18",
                           "image_url":"https://encrypted-tbn0.gstatic.com/images?q=tbn:ANd9GcQuvP0Ijdg9Nf3gI2h83aMz33fl_XLsqpKZPGc0tX_6RQmLa83O",
                           "price":"13",
                           "tag":{
                           "id":4,
                           "name":"Travaux"
                           },
                           "user": {
                           "id":40829,
                           "firstname":"thomas",
                           "lastname":"donninger",
                           "email":"tom@voodoo.fr",
                           "image_url":"https://www.tm-town.com/assets/default_male600x600-79218392a28f78af249216e097aaf683.png"
                           }
                           },
                           {
                           "id":4,
                           "title":"Demande n°4",
                           "description":"Lorem ipsum dolor sit amet, consectetur adipiscing elit. Phasellus eu lorem sit amet nibh pretium aliquet sit amet at nulla. Cras malesuada ligula arcu, luctus laoreet turpis rhoncus eu. Proin mattis, orci et lobortis finibus, lacus erat fermentum massa, sit amet tempus elit massa eu enim. Etiam mattis, dui ut mollis blandit, eros risus rutrum metus, ac ornare mauris mi sed augue. Duis convallis massa id metus convallis mattis. Nunc vestibulum feugiat nisl eget tempor. Nam consectetur magna augue, quis condimentum sem interdum sed.",
                           "city":"Paris 18",
                           "image_url":"https://www.anact.fr/sites/anact/files/styles/780x503/public/aide-domicile-cas-entreprise.png?itok=9ig_Pm4l",
                           "price":"15",
                           "tag":{
                           "id":3,
                           "name":"Aide à domicile"
                           },
                           "user": {
                           "id":40830,
                           "firstname":"Jeanne",
                           "lastname":"Dubois",
                           "email":"jeanne@voodoo.fr",
                           "image_url":"https://image.flaticon.com/icons/png/512/163/163833.png"
                           }
                           },
                           {
                           "id":5,
                           "title":"Demande n°5",
                           "description":"Lorem ipsum dolor sit amet, consectetur adipiscing elit. Phasellus eu lorem sit amet nibh pretium aliquet sit amet at nulla. Cras malesuada ligula arcu, luctus laoreet turpis rhoncus eu. Proin mattis, orci et lobortis finibus, lacus erat fermentum massa, sit amet tempus elit massa eu enim. Etiam mattis, dui ut mollis blandit, eros risus rutrum metus, ac ornare mauris mi sed augue. Duis convallis massa id metus convallis mattis. Nunc vestibulum feugiat nisl eget tempor. Nam consectetur magna augue, quis condimentum sem interdum sed.",
                           "city":"Paris 18",
                           "image_url":"https://www.olapromo.com/reduction/coupon-reduction-bricolage.jpg",
                           "price":"20",
                           "tag":{
                           "id":2,
                           "name":"Bricolage"
                           },
                           "user": {
                           "id":40830,
                           "firstname":"Jeanne",
                           "lastname":"Dubois",
                           "email":"jeanne@voodoo.fr",
                           "image_url":"https://image.flaticon.com/icons/png/512/163/163833.png"
                           }
                           }
                           ]
                }
                ]
}

